textelixir/__init__.py
textelixir/collocates.py
textelixir/create_tables.py
textelixir/indexer.py
textelixir/insert_tables.py
textelixir/kwic.py
textelixir/mattr.py
textelixir/ngrams.py
textelixir/reader.py
textelixir/search.py
textelixir/searchdist.py
textelixir/searchwindow.py
textelixir/text_splits.py
textelixir-1.0.5.dist-info/LICENSE
textelixir-1.0.5.dist-info/METADATA
textelixir-1.0.5.dist-info/WHEEL
textelixir-1.0.5.dist-info/top_level.txt
textelixir-1.0.5.dist-info/RECORD
