Metadata-Version: 2.1
Name: textelixir
Version: 1.0.5
Summary: A natural language toolkit designed to facilitate the process of generating collocates, ngrams, KWIC lines, and more.
Home-page: https://github.com/javascriptorian/textelixir
Author: The JavaScriptorian
Author-email: contact@javascriptorian.com
Classifier: Programming Language :: Python :: 3
Classifier: License :: OSI Approved :: MIT License
Classifier: Operating System :: OS Independent
Requires-Python: >=3.7
License-File: LICENSE
Requires-Dist: pandas
Requires-Dist: spacy
Requires-Dist: stanza
Requires-Dist: plotly
Requires-Dist: plotly-express
Requires-Dist: kaleido
Requires-Dist: tqdm
Requires-Dist: numpy
